map_downloader/__init__.py
map_downloader/download.py
map_downloader/opt_parser.py
map_downloader-0.13.data/scripts/map_downloader
map_downloader-0.13.dist-info/DESCRIPTION.rst
map_downloader-0.13.dist-info/METADATA
map_downloader-0.13.dist-info/RECORD
map_downloader-0.13.dist-info/WHEEL
map_downloader-0.13.dist-info/metadata.json
map_downloader-0.13.dist-info/top_level.txt
