Metadata-Version: 2.0
Name: map-downloader
Version: 0.13
Summary: Download map files required by gopher_series robot.
Home-page: https://github.com/yotabits/map_downloader
Author: Thomas Kostas
Author-email: tkostas75@gmail.com
License: MIT
Platform: UNKNOWN
Classifier: Development Status :: 3 - Alpha
Classifier: Intended Audience :: Developers
Classifier: Topic :: Software Development :: Build Tools
Classifier: License :: OSI Approved :: MIT License
Classifier: Programming Language :: Python :: 2.7
Requires-Dist: requests (==2.19.1)
